MANIFEST.in
README.md
requirements.txt
setup.py
pynemo/__init__.py
pynemo.egg-info/PKG-INFO
pynemo.egg-info/SOURCES.txt
pynemo.egg-info/dependency_links.txt
pynemo.egg-info/requires.txt
pynemo.egg-info/top_level.txt
pynemo/core/__init__.py
pynemo/core/util.py
pynemo/core/base/__init__.py
pynemo/core/base/abstract/__init__.py
pynemo/core/base/abstract/expression.py
pynemo/core/base/abstract/operation.py
pynemo/core/base/abstract/property.py
pynemo/core/base/model/__init__.py
pynemo/core/base/model/node.py
pynemo/core/base/model/relationship.py
pynemo/core/base/operation/__init__.py
pynemo/core/base/operation/create.py
pynemo/core/base/operation/match.py
pynemo/core/base/operation/return_values.py
pynemo/core/base/property/__init__.py
pynemo/core/base/property/boolean.py
pynemo/core/base/property/floating.py
pynemo/core/base/property/integer.py
pynemo/core/base/property/string.py
pynemo/core/base/statement/__init__.py
pynemo/core/base/statement/statement.py